metal_gpu/__init__.py
metal_gpu/add.py
metal_gpu-0.1.1.dist-info/METADATA
metal_gpu-0.1.1.dist-info/WHEEL
metal_gpu-0.1.1.dist-info/licenses/LICENSE
metal_gpu-0.1.1.dist-info/RECORD
