Metadata-Version: 2.3
Name: metal-gpu
Version: 0.1.1
Summary: A python wrapper for Apple's Metal API
Author-email: aloisdenoiseux@example.com
License-File: LICENSE
Classifier: License :: OSI Approved :: MIT License
Classifier: Operating System :: MacOS :: MacOS X
Classifier: Programming Language :: Python :: 3
Requires-Python: >=3.1
